ppio_agent_runtime/__init__.py
ppio_agent_runtime/exceptions.py
ppio_agent_runtime/runtime/__init__.py
ppio_agent_runtime/runtime/app.py
ppio_agent_runtime/runtime/context.py
ppio_agent_runtime/runtime/models.py
ppio_agent_runtime/runtime/server.py
ppio_agent_runtime-0.1.0.dist-info/METADATA
ppio_agent_runtime-0.1.0.dist-info/WHEEL
ppio_agent_runtime-0.1.0.dist-info/RECORD
