Metadata-Version: 2.4
Name: ppio-agent-runtime
Version: 0.1.0
Summary: PPIO Agent Runtime SDK - 轻量级 AI 智能体运行时框架
Project-URL: Homepage, https://github.com/ppio/ppio-agent-runtime-sdk
Project-URL: Documentation, https://github.com/ppio/ppio-agent-runtime-sdk#readme
Project-URL: Repository, https://github.com/ppio/ppio-agent-runtime-sdk.git
Project-URL: Issues, https://github.com/ppio/ppio-agent-runtime-sdk/issues
Author-email: PPIO Team <team@ppio.cn>
License: MIT
Classifier: Development Status :: 3 - Alpha
Classifier: Intended Audience :: Developers
Classifier: License :: OSI Approved :: MIT License
Classifier: Programming Language :: Python :: 3
Classifier: Programming Language :: Python :: 3.8
Classifier: Programming Language :: Python :: 3.9
Classifier: Programming Language :: Python :: 3.10
Classifier: Programming Language :: Python :: 3.11
Classifier: Programming Language :: Python :: 3.12
Classifier: Topic :: Scientific/Engineering :: Artificial Intelligence
Classifier: Topic :: Software Development :: Libraries :: Python Modules
Requires-Python: >=3.12
Requires-Dist: pydantic<3.0.0,>=2.0.0
Requires-Dist: starlette>=0.46.2
Requires-Dist: typing-extensions<5.0.0,>=4.13.2
Requires-Dist: uvicorn>=0.34.2
Provides-Extra: dev
Requires-Dist: httpx>=0.28.1; extra == 'dev'
Requires-Dist: mypy>=1.16.1; extra == 'dev'
Requires-Dist: pytest-asyncio>=0.24.0; extra == 'dev'
Requires-Dist: pytest>=8.4.1; extra == 'dev'
Requires-Dist: ruff>=0.12.0; extra == 'dev'
